{
  "workbench.colorTheme": "Default Light+",
  "editor.renderWhitespace": "all",
  "editor.bracketPairColorization.independentColorPoolPerBracketType": true,
  "editor.formatOnSave": true,
  "workbench.iconTheme": "vscode-icons",
  "vsicons.dontShowNewVersionMessage": true,
  "[typescriptreact]": {
    "editor.defaultFormatter": "esbenp.prettier-vscode"
  },
  "[typescript]": {
    "editor.defaultFormatter": "esbenp.prettier-vscode"
  },
  "[scss]": {
    "editor.defaultFormatter": "esbenp.prettier-vscode"
  },
  "[json]": {
    "editor.defaultFormatter": "esbenp.prettier-vscode"
  },
  "[javascript]": {
    "editor.defaultFormatter": "esbenp.prettier-vscode"
  },
  "editor.fontLigatures": true,
  "editor.fontFamily": "'Fira Code','Droid Sans Mono', 'monospace', monospace",
  "terminal.integrated.defaultProfile.linux": "zsh",
  "terminal.integrated.fontFamily": "'Fira Code'",
  "javascript.updateImportsOnFileMove.enabled": "always",
  "typescript.updateImportsOnFileMove.enabled": "always",
  "editor.minimap.enabled": false
}
